Metadata-Version: 2.1
Name: eflow
Version: 0.2.46.15
Summary: UNKNOWN
Home-page: https://github.com/EricCacciavillani/eFlow
Author: Eric Cacciavillani
Author-email: eric.cacciavillani@gmail.com
License: UNKNOWN
Platform: UNKNOWN
Classifier: Programming Language :: Python :: 3.7
Classifier: License :: OSI Approved :: MIT License
Classifier: Operating System :: OS Independent
Requires-Dist: numpy
Requires-Dist: matplotlib
Requires-Dist: scipy
Requires-Dist: seaborn
Requires-Dist: jupyterlab
Requires-Dist: pandas
Requires-Dist: missingno
Requires-Dist: sklearn
Requires-Dist: kneed
Requires-Dist: tqdm
Requires-Dist: Pillow
Requires-Dist: python-dateutil
Requires-Dist: scikit-plot
Requires-Dist: ipywidgets
Requires-Dist: nltk
Requires-Dist: pyclustering
Requires-Dist: plotly
